power01_plus/__init__.py
power01_plus/plus.py
power01_plus-0.1.1.dist-info/METADATA
power01_plus-0.1.1.dist-info/WHEEL
power01_plus-0.1.1.dist-info/entry_points.txt
power01_plus-0.1.1.dist-info/top_level.txt
power01_plus-0.1.1.dist-info/RECORD
