Metadata-Version: 2.1
Name: power01_plus
Version: 0.1.1
Summary: Default template for PDM package
Author-email: baechu805 <bjoo606@naver.com>
License: MIT
Requires-Python: >=3.9
